rocm_vvv/__init__.py
rocm_vvv/__main__.py
rocm_vvv/checker.py
rocm_vvv/component_detectors.py
rocm_vvv-0.0.8.dist-info/licenses/LICENSE
tests/__init__.py
tests/test_checker.py
rocm_vvv-0.0.8.dist-info/METADATA
rocm_vvv-0.0.8.dist-info/WHEEL
rocm_vvv-0.0.8.dist-info/entry_points.txt
rocm_vvv-0.0.8.dist-info/top_level.txt
rocm_vvv-0.0.8.dist-info/RECORD
