Metadata-Version: 2.4
Name: rocm-vvv
Version: 0.0.8
Summary: A comprehensive ROCm ecosystem version checker with colorful output
Author-email: JeongHyun Kim <jeonghyun.kim@amd.com>
License-Expression: MIT
Project-URL: Homepage, https://github.com/JH-Leon-KIM-AMD/rocm-vvv
Project-URL: Bug Reports, https://github.com/JH-Leon-KIM-AMD/rocm-vvv/issues
Project-URL: Source, https://github.com/JH-Leon-KIM-AMD/rocm-vvv
Keywords: rocm,amd,gpu,version,checker,hip,miopen,rocblas,vvv
Classifier: Development Status :: 4 - Beta
Classifier: Intended Audience :: Developers
Classifier: Intended Audience :: System Administrators
Classifier: Topic :: System :: Hardware
Classifier: Topic :: System :: Systems Administration
Classifier: Topic :: Software Development :: Libraries :: Python Modules
Classifier: Programming Language :: Python :: 3
Classifier: Programming Language :: Python :: 3.6
Classifier: Programming Language :: Python :: 3.7
Classifier: Programming Language :: Python :: 3.8
Classifier: Programming Language :: Python :: 3.9
Classifier: Programming Language :: Python :: 3.10
Classifier: Programming Language :: Python :: 3.11
Classifier: Programming Language :: Python :: 3.12
Classifier: Operating System :: POSIX :: Linux
Requires-Python: >=3.6
License-File: LICENSE
Dynamic: license-file
